galaxy_test/__init__.py
galaxy_test/selenium/__init__.py
galaxy_test/selenium/conftest.py
galaxy_test/selenium/framework.py
galaxy_test/selenium/jupyter_context.py
galaxy_test/selenium/test_admin_app.py
galaxy_test/selenium/test_anon_history.py
galaxy_test/selenium/test_change_password.py
galaxy_test/selenium/test_collection_builders.py
galaxy_test/selenium/test_collection_edit.py
galaxy_test/selenium/test_custom_builds.py
galaxy_test/selenium/test_data_source_tools.py
galaxy_test/selenium/test_histories_list.py
galaxy_test/selenium/test_history_copy_elements.py
galaxy_test/selenium/test_history_dataset_state.py
galaxy_test/selenium/test_history_export.py
galaxy_test/selenium/test_history_multi_view.py
galaxy_test/selenium/test_history_options.py
galaxy_test/selenium/test_history_panel.py
galaxy_test/selenium/test_history_panel_collections.py
galaxy_test/selenium/test_history_panel_pagination.py
galaxy_test/selenium/test_history_sharing.py
galaxy_test/selenium/test_history_structure.py
galaxy_test/selenium/test_jupyter.py
galaxy_test/selenium/test_library_contents.py
galaxy_test/selenium/test_library_landing.py
galaxy_test/selenium/test_library_to_collections.py
galaxy_test/selenium/test_login.py
galaxy_test/selenium/test_navigates_galaxy.py
galaxy_test/selenium/test_pages.py
galaxy_test/selenium/test_personal_information.py
galaxy_test/selenium/test_published_histories_grid.py
galaxy_test/selenium/test_registration.py
galaxy_test/selenium/test_sign_out.py
galaxy_test/selenium/test_sizzle_loading.py
galaxy_test/selenium/test_stock_tours.py
galaxy_test/selenium/test_tool_describing_tours.py
galaxy_test/selenium/test_tool_form.py
galaxy_test/selenium/test_uploads.py
galaxy_test/selenium/test_workflow_editor.py
galaxy_test/selenium/test_workflow_invocation_details.py
galaxy_test/selenium/test_workflow_management.py
galaxy_test/selenium/test_workflow_run.py
galaxy_test/selenium/test_workflow_sharing.py
galaxy_test/selenium/jupyter/__init__.py
galaxy_test_selenium-22.1.1.dist-info/LICENSE
galaxy_test_selenium-22.1.1.dist-info/METADATA
galaxy_test_selenium-22.1.1.dist-info/WHEEL
galaxy_test_selenium-22.1.1.dist-info/entry_points.txt
galaxy_test_selenium-22.1.1.dist-info/top_level.txt
galaxy_test_selenium-22.1.1.dist-info/RECORD
